{"preferred_name": "Adrian Thieret", "profile_picture": "https://cdn.shanghai.nyu.edu/sites/default/files/field/profile/directoryphoto.jpg", "official_title": "Global Perspectives on Society Teaching Fellow", "email_address": "N/A", "room_number": "N/A", "office_phone": "N/A", "bio": "<div class=\"panel-pane pane-faculty-member-bio\">\n<div class=\"field field-name-body field-type-text-with-summary field-label-hidden\">\n<div class=\"field-items\">\n<div class=\"field-item even\" property=\"content:encoded\"><p>Adrian Thieret is a Global Perspectives on Society Teaching Fellow at NYU Shanghai. He holds a Ph.D. in Chinese from Stanford University and a B.A. in Asian Languages and Literatures from the University of Minnesota: Twin Cities.<br/><br/>Dr. Thieret researches contemporary East Asian literature and popular culture. His current project clarifies the history and canonization of science fiction in China and across China, Korea, and Japan. He is particularly interested in utopianism, ecology, and transnational cultural flows as related to conceptions of the national and the cosmopolitan. His research has appeared in China Perspectives and his translations of fiction and nonfiction from Chinese and Korean into English have been published in a number of venues.</p><p>Some of Dr. Thieret\u2019s academic appointments prior to joining NYU Shanghai include as Lecturer in East Asian Studies at McGill University, as Lecturer in Chinese at the University of California: Santa Cruz, and three summers as Resident Director of a NSLIY\u00a0China summer study abroad program (201517). He was a Blakemore Freeman Fellow to Korea in 2012-13.</p><h3>Education</h3><ul><li>Ph.D., Chinese, Stanford University, 2016</li><li>B.A., Asian Languages, and Literatures, University of Minnesota: Twin Cities, 2008</li></ul><h3>Languages</h3><ul><li>Chinese</li><li>English</li><li>Japanese, Korean</li></ul></div>\n</div>\n</div>\n</div>"}