{"preferred_name": "Zhehua Li", "profile_picture": "https://cdn.shanghai.nyu.edu/sites/default/files/field/profile/zhehua_li_photo.jpg", "official_title": "Postdoctoral Fellow", "email_address": "zl526@nyu.edu", "room_number": "N/A", "office_phone": "N/A", "bio": "<div class=\"panel-pane pane-faculty-member-bio\">\n<div class=\"field field-name-body field-type-text-with-summary field-label-hidden\">\n<div class=\"field-items\">\n<div class=\"field-item even\" property=\"content:encoded\"><p>Zhehua Li is currently a Postdoc fellow at NYU Shanghai. He obtained his Ph.D. from University of California, San Diego under the supervision of Prof. Bruce Driver. His research interests lie in the intersection of probability and differential geometry.</p><h3>Research Interests:</h3><ul><li>Stochastic analysis on manifolds</li><li>Mallavin calculus</li><li>SPDE and Mathematical physics</li><li>Discrete Probability</li></ul><h3>Courses Taught:</h3><ul><li>Recitation of\u00a0MATH-SHU 235 Probability and Statistics</li><li><p>MATH-SHU 123 Multivariable calculus\u00a0(Spring 2017)\u00a0</p></li></ul><h3>Education:</h3><ul><li><p>BS, Mathematics, Fudan University, China, 2011</p></li><li><p>Ph.D. Mathematics, University of California, San Diego, USA 2016</p></li></ul><p>\u00a0</p></div>\n</div>\n</div>\n</div>"}